flask_cblueprint/__init__.py
flask_cblueprint/config.py
flask_cblueprint/flask_cblueprint.py
flask_cblueprint/commands/__init__.py
flask_cblueprint/commands/create_blueprint.py
flask_cblueprint/commands/list_blueprint.py
flask_cblueprint/utils/__init__.py
flask_cblueprint/utils/filesystem.py
flask_cblueprint/utils/list.py
flask_cblueprint/utils/string.py
flask_cblueprint/utils/validate.py
Flask_CBlueprint-1.0.0.dist-info/LICENSE
Flask_CBlueprint-1.0.0.dist-info/METADATA
Flask_CBlueprint-1.0.0.dist-info/WHEEL
Flask_CBlueprint-1.0.0.dist-info/top_level.txt
Flask_CBlueprint-1.0.0.dist-info/RECORD
