Metadata-Version: 2.1
Name: Flask-CBlueprint
Version: 1.0.0
Home-page: https://github.com/Sigurd06/flask-cblueprint/tree/main
Download-URL: https://github.com/Sigurd06/flask-cblueprint/tree/v1.0.0
Author: Camilo Vargas
Author-email: bomilo66@gmail.com
License: MIT
Project-URL: Documentation, https://pypi.org/project/Flask-CBlueprint/
Project-URL: Source Code, https://github.com/Sigurd06/flask-cblueprint
Project-URL: Issue Tracker, https://github.com/Sigurd06/flask-cblueprint/issues
Classifier: Programming Language :: Python :: 3
Classifier: License :: OSI Approved :: MIT License
Classifier: Operating System :: OS Independent
Requires-Python: >=3
License-File: LICENSE
Requires-Dist: Flask (>=1.0.4)
Requires-Dist: Werkzeug (>=1.0.1)
Requires-Dist: click (>=8.1.3)
Requires-Dist: MarkupSafe (>=2.1.2)
Requires-Dist: python-dotenv (>=1.0.0)
Requires-Dist: simple-term-menu (>=1.6.1)
